[
    {
        "key": "datr",
        "value": "GgkZZ-Ke1GwtUDUr_6agjva_",
        "domain": "facebook.com",
        "path": "/",
        "hostOnly": false,
        "creation": "2024-11-14T12:12:33.812Z",
        "lastAccessed": "2024-11-14T12:12:33.812Z"
    },
    {
        "key": "sb",
        "value": "GgkZZ7dE_PCfqGdBnlddx1ND",
        "domain": "facebook.com",
        "path": "/",
        "hostOnly": false,
        "creation": "2024-11-14T12:12:33.812Z",
        "lastAccessed": "2024-11-14T12:12:33.812Z"
    },
    {
        "key": "ps_l",
        "value": "1",
        "domain": "facebook.com",
        "path": "/",
        "hostOnly": false,
        "creation": "2024-11-14T12:12:33.812Z",
        "lastAccessed": "2024-11-14T12:12:33.812Z"
    },
    {
        "key": "ps_n",
        "value": "1",
        "domain": "facebook.com",
        "path": "/",
        "hostOnly": false,
        "creation": "2024-11-14T12:12:33.812Z",
        "lastAccessed": "2024-11-14T12:12:33.812Z"
    },
    {
        "key": "c_user",
        "value": "100071677211067",
        "domain": "facebook.com",
        "path": "/",
        "hostOnly": false,
        "creation": "2024-11-14T12:12:33.812Z",
        "lastAccessed": "2024-11-14T12:12:33.812Z"
    },
    {
        "key": "fr",
        "value": "0YmAVeVQPIfol4HVp.AWX9MImCUyJ34Qp2r6J3eBt2RRI.BnMx2u..AAA.0.0.BnM8_R.AWVq_jDeSsY",
        "domain": "facebook.com",
        "path": "/",
        "hostOnly": false,
        "creation": "2024-11-14T12:12:33.812Z",
        "lastAccessed": "2024-11-14T12:12:33.812Z"
    },
    {
        "key": "xs",
        "value": "13%3AXseLAShF9M47Ew%3A2%3A1731448786%3A-1%3A5181",
        "domain": "facebook.com",
        "path": "/",
        "hostOnly": false,
        "creation": "2024-11-14T12:12:33.812Z",
        "lastAccessed": "2024-11-14T12:12:33.812Z"
    },
    {
        "key": "vpd",
        "value": "v1%3B785x393x2.75",
        "domain": "facebook.com",
        "path": "/",
        "hostOnly": false,
        "creation": "2024-11-14T12:12:33.812Z",
        "lastAccessed": "2024-11-14T12:12:33.812Z"
    },
    {
        "key": "locale",
        "value": "en_GB",
        "domain": "facebook.com",
        "path": "/",
        "hostOnly": false,
        "creation": "2024-11-14T12:12:33.812Z",
        "lastAccessed": "2024-11-14T12:12:33.812Z"
    },
    {
        "key": "m_pixel_ratio",
        "value": "2.75",
        "domain": "facebook.com",
        "path": "/",
        "hostOnly": false,
        "creation": "2024-11-14T12:12:33.812Z",
        "lastAccessed": "2024-11-14T12:12:33.812Z"
    },
    {
        "key": "wd",
        "value": "393x785",
        "domain": "facebook.com",
        "path": "/",
        "hostOnly": false,
        "creation": "2024-11-14T12:12:33.812Z",
        "lastAccessed": "2024-11-14T12:12:33.812Z"
    },
    {
        "key": "wl_cbv",
        "value": "v2%3Bclient_version%3A2673%3Btimestamp%3A1731586018",
        "domain": "facebook.com",
        "path": "/",
        "hostOnly": false,
        "creation": "2024-11-14T12:12:33.812Z",
        "lastAccessed": "2024-11-14T12:12:33.812Z"
    },
    {
        "key": "fbl_st",
        "value": "101525193%3BT%3A28859767",
        "domain": "facebook.com",
        "path": "/",
        "hostOnly": false,
        "creation": "2024-11-14T12:12:33.812Z",
        "lastAccessed": "2024-11-14T12:12:33.812Z"
    }
]
